cbr_website_beta/__init__.py
cbr_website_beta/__main__.py
cbr_website_beta/_caches/__init__.py
cbr_website_beta/_caches/dydb_chat_threads/Sqlite__DyDB__Chat_Threads.py
cbr_website_beta/_caches/dydb_chat_threads/__init__.py
cbr_website_beta/_cbr_shared/__init__.py
cbr_website_beta/_cbr_shared/dynamo_db/DyDB__CBR_Chat_Threads.py
cbr_website_beta/_cbr_shared/dynamo_db/DyDB__CBR_Logging.py
cbr_website_beta/_cbr_shared/dynamo_db/DyDB__CBR_Requests.py
cbr_website_beta/_cbr_shared/dynamo_db/DyDB__CBR_User_Sessions.py
cbr_website_beta/_cbr_shared/dynamo_db/__init__.py
cbr_website_beta/_cbr_shared/schemas/CBR_Logging.py
cbr_website_beta/_cbr_shared/schemas/CBR_Request.py
cbr_website_beta/_cbr_shared/schemas/__init__.py
cbr_website_beta/_testing/__init.py
cbr_website_beta/_testing/test_utils/TestCase__CBR__Website.py
cbr_website_beta/_testing/website/CBR_Website.py
cbr_website_beta/_testing/website/CBR__Login.py
cbr_website_beta/_testing/website/CBR__Pages.py
cbr_website_beta/_to_refactor_out/RSS_Data_Feeds.py
cbr_website_beta/apps/__init__.py
cbr_website_beta/apps/chat/__init__.py
cbr_website_beta/apps/chat/chat_routes.py
cbr_website_beta/apps/config.py
cbr_website_beta/apps/dev/Render_Panels.py
cbr_website_beta/apps/dev/Render_Panels__Test_Data.py
cbr_website_beta/apps/dev/__init__.py
cbr_website_beta/apps/dev/dev_routes.py
cbr_website_beta/apps/dev/odin/Odin__Panels__Dashboard_Widgets.py
cbr_website_beta/apps/dev/odin/Odin__Panels__Debug.py
cbr_website_beta/apps/dev/odin/Odin__Panels__Logs.py
cbr_website_beta/apps/dev/odin/Odin__Panels__Real_Time.py
cbr_website_beta/apps/dev/odin/Odin__Panels__Session_Management.py
cbr_website_beta/apps/dev/view_data.py
cbr_website_beta/apps/dev/views/Debug_Views.py
cbr_website_beta/apps/dev/views/Logs_Views.py
cbr_website_beta/apps/dev/views/Real_Time_Views.py
cbr_website_beta/apps/dev/views/Render_View.py
cbr_website_beta/apps/dev/views/Users_Views.py
cbr_website_beta/apps/docs/__init__.py
cbr_website_beta/apps/docs/docs_routes.py
cbr_website_beta-0.221.1.dist-info/LICENSE-for-new-code.txt
cbr_website_beta-0.221.1.dist-info/LICENSE.md
cbr_website_beta-0.221.1.dist-info/METADATA
cbr_website_beta-0.221.1.dist-info/WHEEL
cbr_website_beta-0.221.1.dist-info/RECORD
