Metadata-Version: 2.1
Name: cbr-website-beta
Version: 0.221.1
Summary: CBR Website - Beta
Home-page: https://github.com/the-cyber-boardroom/cbr-website-beta
License: MIT
Author: Dinis Cruz
Author-email: dinis.cruz@owasp.org
Requires-Python: >=3.11,<4.0
Classifier: License :: OSI Approved :: MIT License
Classifier: Programming Language :: Python :: 3
Classifier: Programming Language :: Python :: 3.11
Classifier: Programming Language :: Python :: 3.12
Classifier: Programming Language :: Python :: 3.13
Requires-Dist: boto3
Requires-Dist: cbr-athena
Requires-Dist: cbr-content
Requires-Dist: cbr-shared
Requires-Dist: cbr-static
Requires-Dist: cbr-user-session
Requires-Dist: cbr-web-components
Requires-Dist: fastapi
Requires-Dist: flask
Requires-Dist: osbot-aws
Requires-Dist: osbot-fast-api
Requires-Dist: osbot-local-stack
Requires-Dist: osbot-markdown
Requires-Dist: osbot-utils
Requires-Dist: pydantic
Requires-Dist: python-dotenv
Requires-Dist: requests
Requires-Dist: werkzeug
